caa_v22/.DS_Store
caa_v22/__init__.py
caa_v22/confs.py
caa_v22/merge.py
caa_v22/modifiers.py
caa_v22/patch.py
caa_v22/utils.py
caa_v22-0.1.5.dist-info/LICENSE.txt
caa_v22-0.1.5.dist-info/METADATA
caa_v22-0.1.5.dist-info/WHEEL
caa_v22-0.1.5.dist-info/RECORD
